.version
LICENSE.txt
MANIFEST.in
README.rst
setup.cfg
setup.py
oi/__init__.py
oi/oi.py
oicli.egg-info/PKG-INFO
oicli.egg-info/SOURCES.txt
oicli.egg-info/dependency_links.txt
oicli.egg-info/top_level.txt