Metadata-Version: 1.1
Name: oicli
Version: 0.3.0
Summary: Simple command-line parser.
Home-page: https://gitlab.com/cathaldallan/oi
Author: Wilson Santos
Author-email: wilson@codeminus.org
License: MIT
Keywords: cli argparse command-line interface
Platform: UNKNOWN
Classifier: Programming Language :: Python :: 2.7
Classifier: Programming Language :: Python :: 3
